predictor_gradient_descent/__init__.py
predictor_gradient_descent/main.py
predictor_gradient_descent-0.1.0.dist-info/METADATA
predictor_gradient_descent-0.1.0.dist-info/WHEEL
predictor_gradient_descent-0.1.0.dist-info/top_level.txt
predictor_gradient_descent-0.1.0.dist-info/RECORD
