Metadata-Version: 2.1
Name: predictor_gradient_descent
Version: 0.1.0
Summary: A library which Predicts the Y value(output) for given test data points using gradient descent algorithm.
Author: K ABHISHEK MENON
Author-email: kabhishekmenon@gmail.com
Classifier: Programming Language :: Python :: 3
Classifier: License :: OSI Approved :: MIT License
Classifier: Operating System :: OS Independent
Requires-Python: >=3.6
